nvflare/__init__.py
nvflare/_version.py
nvflare/apis/__init__.py
nvflare/apis/fl_constant.py
nvflare/app_common/__init__.py
nvflare/app_common/decomposers/__init__.py
nvflare/app_common/decomposers/numpy_decomposers.py
nvflare/client/__init__.py
nvflare/client/ipc/__init__.py
nvflare/client/ipc/defs.py
nvflare/client/ipc/ipc_agent.py
nvflare/fuel/__init__.py
nvflare/fuel/common/__init__.py
nvflare/fuel/common/ctx.py
nvflare/fuel/common/excepts.py
nvflare/fuel/common/exit_codes.py
nvflare/fuel/common/multi_process_executor_constants.py
nvflare/fuel/f3/__init__.py
nvflare/fuel/f3/comm_config.py
nvflare/fuel/f3/comm_error.py
nvflare/fuel/f3/communicator.py
nvflare/fuel/f3/connection.py
nvflare/fuel/f3/endpoint.py
nvflare/fuel/f3/message.py
nvflare/fuel/f3/mpm.py
nvflare/fuel/f3/stats_pool.py
nvflare/fuel/f3/stream_cell.py
nvflare/fuel/f3/cellnet/__init__.py
nvflare/fuel/f3/cellnet/cbs.py
nvflare/fuel/f3/cellnet/cell.py
nvflare/fuel/f3/cellnet/cell_cipher.py
nvflare/fuel/f3/cellnet/connector_manager.py
nvflare/fuel/f3/cellnet/core_cell.py
nvflare/fuel/f3/cellnet/credential_manager.py
nvflare/fuel/f3/cellnet/defs.py
nvflare/fuel/f3/cellnet/fqcn.py
nvflare/fuel/f3/cellnet/net_agent.py
nvflare/fuel/f3/cellnet/net_manager.py
nvflare/fuel/f3/cellnet/registry.py
nvflare/fuel/f3/cellnet/utils.py
nvflare/fuel/f3/drivers/__init__.py
nvflare/fuel/f3/drivers/aio_conn.py
nvflare/fuel/f3/drivers/aio_context.py
nvflare/fuel/f3/drivers/aio_tcp_driver.py
nvflare/fuel/f3/drivers/base_driver.py
nvflare/fuel/f3/drivers/connector_info.py
nvflare/fuel/f3/drivers/driver.py
nvflare/fuel/f3/drivers/driver_manager.py
nvflare/fuel/f3/drivers/driver_params.py
nvflare/fuel/f3/drivers/net_utils.py
nvflare/fuel/f3/drivers/socket_conn.py
nvflare/fuel/f3/drivers/tcp_driver.py
nvflare/fuel/f3/sfm/__init__.py
nvflare/fuel/f3/sfm/conn_manager.py
nvflare/fuel/f3/sfm/constants.py
nvflare/fuel/f3/sfm/heartbeat_monitor.py
nvflare/fuel/f3/sfm/prefix.py
nvflare/fuel/f3/sfm/sfm_conn.py
nvflare_light_nightly-2.5.1.dist-info/LICENSE
nvflare_light_nightly-2.5.1.dist-info/METADATA
nvflare_light_nightly-2.5.1.dist-info/WHEEL
nvflare_light_nightly-2.5.1.dist-info/entry_points.txt
nvflare_light_nightly-2.5.1.dist-info/top_level.txt
nvflare_light_nightly-2.5.1.dist-info/zip-safe
nvflare_light_nightly-2.5.1.dist-info/RECORD
